COPYING
MANIFEST.in
README.rst
buildout.cfg
pyproject.toml
requirements.txt
setup.py
version.txt
bob/__init__.py
bob.io.stream.egg-info/PKG-INFO
bob.io.stream.egg-info/SOURCES.txt
bob.io.stream.egg-info/dependency_links.txt
bob.io.stream.egg-info/not-zip-safe
bob.io.stream.egg-info/requires.txt
bob.io.stream.egg-info/top_level.txt
bob/io/__init__.py
bob/io/stream/__init__.py
bob/io/stream/config.py
bob/io/stream/stream.py
bob/io/stream/stream_file.py
bob/io/stream/stream_image_filters.py
bob/io/stream/utils.py
bob/io/stream/config/idiap_face_streams.json
bob/io/stream/test/__init__.py
bob/io/stream/test/test.py
bob/io/stream/test/test_utils.py
bob/io/stream/test/data/gt_colormap_bone.png
bob/io/stream/test/data/gt_colormap_gray.png
bob/io/stream/test/data/gt_swir_norm.png
bob/io/stream/test/data/gt_thermal_clean.png
bob/io/stream/test/data/input_example.h5
bob/io/stream/test/data/swir_940_dark_subtract.png
doc/api.rst
doc/conf.py
doc/index.rst
doc/links.rst
doc/img/bob-128x128.png
doc/img/bob-favicon.ico
doc/img/bob-logo.png