Metadata-Version: 1.1
Name: bob.io.stream
Version: 1.0.0
Summary: New package
Home-page: https://gitlab.idiap.ch/bob/bob.io.stream
Author: David Geissbuhler
Author-email: david.geissbuhler@idiap.ch
License: GPLv3
Keywords: bob
Platform: UNKNOWN
Classifier: Framework :: Bob
Classifier: Development Status :: 4 - Beta
Classifier: Intended Audience :: Science/Research
Classifier: License :: OSI Approved :: GNU General Public License v3 (GPLv3)
Classifier: Natural Language :: English
Classifier: Programming Language :: Python
Classifier: Programming Language :: Python :: 3
Classifier: Topic :: Scientific/Engineering :: Artificial Intelligence
Classifier: Topic :: Software Development :: Libraries :: Python Modules
